Workbook

Sheet Raw_Data (3)
A1: Customer_ID | B1: Account_Number | C1: Customer_Name | D1: Transaction_Date | E1: Transaction_Type | F1: Amount | G1: Currency | H1: Branch_Code | I1: Transaction_ID | J1: Notes | K1: Name_DOB_Combined
A2: CUST-1001 | B2: ACC-884521 | C2: Priya Sharma | D2: 2026-08-01 | E2: Credit | F2: 15000 | G2: INR | H2: BRN-01 | I2: TXN-0001 | J2: Salary credit for August | K2: Priya Sharma | 1990-04-12
A3: CUST-1002 | B3: ACC-774832 | C3: RAHUL MEHTA | D3: 2026-08-02 | E3: DEBIT | F3: $8,500.00 | G3: INR | H3: BRN-02 | I3: TXN-0002 | J3: Online transfer to vendor | K3: RAHUL MEHTA | 1985-11-30
A4: 1003 | B4: ACC-663741 | C4: ananya iyer | D4: 01/08/2026 | E4: credit | F4: 22000 | G4: INR | I4: TXN-0003 | J4: Loan disbursement [SYS] | K4: ananya iyer | 1993-07-08 | U4: 46235
A5: CUST-1004 | B5: ACC-552630 | C5: Vikram Singh | D5: 2026-08-04 | E5: Debit | F5: 3750 | G5: INR | H5: BRN-01 | I5: TXN-0004 | J5: ATM withdrawal | K5: Vikram Singh | 1978-02-25
A6: CUST-1005 | B6: ACC-441519 | C6: Sneha Nair | D6: 2026-08-05 | E6: Credit | F6: 9800 | G6: INR | H6: BRN-03 | I6: TXN-0003 | J6: Freelance payment received | K6: Sneha Nair | 1995-09-14 | U6: 46266
A7: CUST -1006 | B7: ACC-330408 | C7: AMIT PATEL | D7: 2026-08-06 | E7: DEBIT | F7: 1,200.50 | G7: INR | H7: BRN-02 | I7: TXN-0006 | J7: Utility bill payment | K7: AMIT PATEL | 1982-06-03
A8: CUST-1007 | B8: ACC-229397 | C8: ritu gupta | D8: 2026-08-07 | E8: debit | F8: 500 | G8: INR | H8: BRN-04 | I8: TXN-0007 | J8: Coffee shop payment | K8: ritu gupta | 1999-12-20
A9: CUST-1008 | B9: ACC-118286 | C9: Deepak Verma | D9: 08-Aug-2026 | E9: Credit | F9: $45,000 | G9: INR | I9: TXN-0008 | J9: Property rent collected extra | K9: Deepak Verma | 1975-03-17
A10: CUST-1009 | B10: ACC-007175 | C10: MEENA KRISHNAN | D10: 2026-08-09 | E10: Debit | F10: $2,300.00 | G10: INR | H10: BRN-03 | I10: TXN-0009 | J10: Insurance premium paid | K10: MEENA KRISHNAN | 1988-08-05 | U10: 46236
A11: CUST-1010 | B11: ACC-996064 | C11: Arjun Bose | D11: 2026-08-10 | E11: Credit | F11: 11000 | G11: INR | H11: BRN-01 | I11: TXN-0010 | J11: Dividend received | K11: Arjun Bose | 1991-01-22
A12: 1011 | B12: ACC-885953 | C12: kavya reddy | D12: 2026-08-11 | E12: debit | F12: 750 | G12: INR | H12: BRN-05 | I12: TXN-0011 | J12: Supermarket purchase | K12: kavya reddy | 1996-05-09
A13: CUST-1012 | B13: ACC-774842 | C13: SURESH PILLAI | D13: 2026-08-12 | E13: Credit | F13: N/A | G13: INR | H13: BRN-02 | I13: TXN-0012 | J13: Pending credit | K13: SURESH PILLAI | 1970-10-31
A14: 1003 | B14: ACC-663741 | C14: ananya iyer | D14: 01/08/2026 | E14: credit | F14: 22000 | G14: INR | I14: TXN-0003 | J14: Loan disbursement | K14: ananya iyer | 1993-07-08
A15: CUST-1013 | B15: ACC-553731 | C15: Pooja Desai | D15: 2026-08-14 | E15: Debit | F15: 4200 | G15: INR | H15: BRN-04 | I15: TXN-0013 | J15: EMI payment | K15: Pooja Desai | 1987-02-14
A16: CUST-1014 | B16: ACC-442620 | C16: NIKHIL JOSHI | D16: 2026-08-15 | E16: CREDIT | F16: $18,900 | G16: INR | H16: BRN-01 | I16: TXN-0014 | J16: Consulting fees | K16: NIKHIL JOSHI | 1983-07-07
A17: 1015 | B17: ACC-331509 | C17: preethi menon | D17: 2026-08-16 | E17: debit | F17: 250 | G17: INR | I17: TXN-0015 | J17: Food delivery | K17: preethi menon | 2000-11-11
A18: CUST-1016 | B18: ACC-220398 | C18: Rohit Kumar | D18: 2026-08-17 | E18: Credit | F18: 8000 | G18: INR | H18: BRN-03 | I18: TXN-0016 | J18: Part-time income | K18: Rohit Kumar | 1994-08-19
A19: CUST-1002 | B19: ACC-774832 | C19: RAHUL MEHTA | D19: 2026-08-02 | E19: DEBIT | F19: $8,500.00 | G19: INR | H19: BRN-02 | I19: TXN-0002 | J19: Online transfer to vendor | K19: RAHUL MEHTA | 1985-11-30
A20: CUST-1017 | B20: ACC-119287 | C20: LAKSHMI RAO | D20: 2026-08-19 | E20: Debit | F20: 1,050 | G20: INR | H20: BRN-05 | I20: TXN-0017 | J20: Mobile recharge | K20: LAKSHMI RAO | 1979-04-28
A21: CUST-1018 | B21: ACC-008176 | C21: Harsh Vardhan | D21: 2026-08-20 | E21: Credit | F21: 30000 | G21: INR | H21: BRN-02 | I21: TXN-0018 | J21: Quarterly bonus | K21: Harsh Vardhan | 1986-09-16
A22: CUST-1019 | B22: ACC-997065 | C22: DIVYA NAMBIAR | D22: 21-Aug-2026 | E22: DEBIT | F22: $600 | G22: INR | I22: TXN-0019 | J22: Grocery shopping | K22: DIVYA NAMBIAR | 1992-03-03
A23: CUST-1020 | B23: ACC-886954 | C23: sanjay kapoor | D23: 2026-08-22 | E23: credit | F23: 5500 | G23: INR | H23: BRN-01 | I23: TXN-0020 | J23: Freelance invoice | K23: sanjay kapoor | 1989-12-25
A24: CUST-1021 | B24: ACC-775843 | C24: RADHA KRISHNA | D24: 2026-08-23 | E24: Credit | F24: 12,750 | G24: INR | H24: BRN-03 | I24: TXN-0021 | J24: Rental income | K24: RADHA KRISHNA | 1976-06-30
A25: 1022 | B25: ACC-664732 | C25: mohan lal | D25: 2026-08-24 | E25: debit | F25: 900 | G25: INR | H25: BRN-04 | I25: TXN-0022 | J25: Book purchase | K25: mohan lal | 1998-01-15
A26: CUST-1023 | B26: ACC-553621 | C26: Geeta Pillai | D26: 2026-08-25 | E26: Debit | F26: 2100 | G26: INR | I26: TXN-0023 | J26: School fees | K26: Geeta Pillai | 1984-05-02
A27: CUST -1024 | B27: ACC-442510 | C27: KIRAN BHAT | D27: 2026-08-25 | E27: CREDIT | F27: $7,200.00 | G27: INR | H27: BRN-02 | I27: TXN-0024 | J27: Dividend credit | K27: KIRAN BHAT | 1981-08-21
A28: CUST-1025 | B28: ACC-331399 | C28: nisha thomas | D28: 2026-08-25 | E28: debit | F28: $350 | G28: INR | H28: BRN-05 | I28: TXN-0025 | J28: Streaming subscription | K28: nisha thomas | 2001-03-07
A29: CUST-1026 | B29: ACC-220288 | C29: VISHAL AGARWAL | D29: 2026-08-25 | E29: Credit | F29: 25000 | G29: INR | H29: BRN-01 | I29: TXN-0026 | J29: Project bonus | K29: VISHAL AGARWAL | 1977-11-18
A30: CUST-1027 | B30: ACC-119177 | C30: Sunita Rao | D30: 2026-08-25 | E30: Debit | F30: 1800 | G30: INR | H30: BRN-03 | I30: TXN-0027 | J30: Monthly subscription | K30: Sunita Rao | 1993-06-06
A31: 1028 | B31: ACC-008066 | C31: rajan pillai | D31: 25/08/2026 | E31: credit | F31: 14000 | G31: INR | H31: BRN-04 | I31: TXN-0028 | J31: Salary advance | K31: rajan pillai | 1980-09-29
A33: LEGEND: 🔴 Pink fill = Duplicate row | 🟡 Yellow fill = Blank value | 🟠 Orange text = Inconsistent format | Find hidden chars & spacing issues in Notes column

Sheet Raw_Data-PLAY
A1: Customer_ID | B1: Account_Number | C1: Customer_Name | D1: Transaction_Date | E1: Transaction_Type | F1: Amount | G1: Currency | H1: Branch_Code | I1: Transaction_ID | J1: Notes | K1: Name_DOB_Combined
A2: CUST-1001 | B2: ACC-884521 | C2: Priya Sharma | D2: 2026-08-01 | E2: Credit | F2: 15000 | G2: INR | H2: BRN-01 | I2: TXN-0001 | J2: Salary credit for August | K2: Priya Sharma | 1990-04-12
A3: CUST-1002 | B3: ACC-774832 | C3: RAHUL MEHTA | D3: 2026-08-02 | E3: DEBIT | F3: $8,500.00 | G3: INR | H3: BRN-02 | I3: TXN-0002 | J3: Online transfer to vendor | K3: RAHUL MEHTA | 1985-11-30
A4: 1003 | B4: ACC-663741 | C4: ananya iyer | D4: 01/08/2026 | E4: credit | F4: 22000 | G4: INR | I4: TXN-0003 | J4: Loan disbursement [SYS] | K4: ananya iyer | 1993-07-08
A5: CUST-1004 | B5: ACC-552630 | C5: Vikram Singh | D5: 2026-08-04 | E5: Debit | F5: 3750 | G5: INR | H5: BRN-01 | I5: TXN-0004 | J5: ATM withdrawal | K5: Vikram Singh | 1978-02-25
A6: CUST-1005 | B6: ACC-441519 | C6: Sneha Nair | D6: 2026-08-05 | E6: Credit | F6: 9800 | G6: INR | H6: BRN-03 | I6: TXN-0003 | J6: Freelance payment received | K6: Sneha Nair | 1995-09-14
A7: CUST -1006 | B7: ACC-330408 | C7: AMIT PATEL | D7: 2026-08-06 | E7: DEBIT | F7: 1,200.50 | G7: INR | H7: BRN-02 | I7: TXN-0006 | J7: Utility bill payment | K7: AMIT PATEL | 1982-06-03
A8: CUST-1007 | B8: ACC-229397 | C8: ritu gupta | D8: 2026-08-07 | E8: debit | F8: 500 | G8: INR | H8: BRN-04 | I8: TXN-0007 | J8: Coffee shop payment | K8: ritu gupta | 1999-12-20
A9: CUST-1008 | B9: ACC-118286 | C9: Deepak Verma | D9: 08-Aug-2026 | E9: Credit | F9: $45,000 | G9: INR | I9: TXN-0008 | J9: Property rent collected extra | K9: Deepak Verma | 1975-03-17
A10: CUST-1009 | B10: ACC-007175 | C10: MEENA KRISHNAN | D10: 2026-08-09 | E10: Debit | F10: $2,300.00 | G10: INR | H10: BRN-03 | I10: TXN-0009 | J10: Insurance premium paid | K10: MEENA KRISHNAN | 1988-08-05
A11: CUST-1010 | B11: ACC-996064 | C11: Arjun Bose | D11: 2026-08-10 | E11: Credit | F11: 11000 | G11: INR | H11: BRN-01 | I11: TXN-0010 | J11: Dividend received | K11: Arjun Bose | 1991-01-22
A12: 1011 | B12: ACC-885953 | C12: kavya reddy | D12: 2026-08-11 | E12: debit | F12: 750 | G12: INR | H12: BRN-05 | I12: TXN-0011 | J12: Supermarket purchase | K12: kavya reddy | 1996-05-09
A13: CUST-1012 | B13: ACC-774842 | C13: SURESH PILLAI | D13: 2026-08-12 | E13: Credit | F13: N/A | G13: INR | H13: BRN-02 | I13: TXN-0012 | J13: Pending credit | K13: SURESH PILLAI | 1970-10-31
A14: 1003 | B14: ACC-663741 | C14: ananya iyer | D14: 01/08/2026 | E14: credit | F14: 22000 | G14: INR | I14: TXN-0003 | J14: Loan disbursement | K14: ananya iyer | 1993-07-08
A15: CUST-1013 | B15: ACC-553731 | C15: Pooja Desai | D15: 2026-08-14 | E15: Debit | F15: 4200 | G15: INR | H15: BRN-04 | I15: TXN-0013 | J15: EMI payment | K15: Pooja Desai | 1987-02-14
A16: CUST-1014 | B16: ACC-442620 | C16: NIKHIL JOSHI | D16: 2026-08-15 | E16: CREDIT | F16: $18,900 | G16: INR | H16: BRN-01 | I16: TXN-0014 | J16: Consulting fees | K16: NIKHIL JOSHI | 1983-07-07
A17: 1015 | B17: ACC-331509 | C17: preethi menon | D17: 2026-08-16 | E17: debit | F17: 250 | G17: INR | I17: TXN-0015 | J17: Food delivery | K17: preethi menon | 2000-11-11
A18: CUST-1016 | B18: ACC-220398 | C18: Rohit Kumar | D18: 2026-08-17 | E18: Credit | F18: 8000 | G18: INR | H18: BRN-03 | I18: TXN-0016 | J18: Part-time income | K18: Rohit Kumar | 1994-08-19
A19: CUST-1002 | B19: ACC-774832 | C19: RAHUL MEHTA | D19: 2026-08-02 | E19: DEBIT | F19: $8,500.00 | G19: INR | H19: BRN-02 | I19: TXN-0002 | J19: Online transfer to vendor | K19: RAHUL MEHTA | 1985-11-30
A20: CUST-1017 | B20: ACC-119287 | C20: LAKSHMI RAO | D20: 2026-08-19 | E20: Debit | F20: 1,050 | G20: INR | H20: BRN-05 | I20: TXN-0017 | J20: Mobile recharge | K20: LAKSHMI RAO | 1979-04-28
A21: CUST-1018 | B21: ACC-008176 | C21: Harsh Vardhan | D21: 2026-08-20 | E21: Credit | F21: 30000 | G21: INR | H21: BRN-02 | I21: TXN-0018 | J21: Quarterly bonus | K21: Harsh Vardhan | 1986-09-16
A22: CUST-1019 | B22: ACC-997065 | C22: DIVYA NAMBIAR | D22: 21-Aug-2026 | E22: DEBIT | F22: $600 | G22: INR | I22: TXN-0019 | J22: Grocery shopping | K22: DIVYA NAMBIAR | 1992-03-03
A23: CUST-1020 | B23: ACC-886954 | C23: sanjay kapoor | D23: 2026-08-22 | E23: credit | F23: 5500 | G23: INR | H23: BRN-01 | I23: TXN-0020 | J23: Freelance invoice | K23: sanjay kapoor | 1989-12-25
A24: CUST-1021 | B24: ACC-775843 | C24: RADHA KRISHNA | D24: 2026-08-23 | E24: Credit | F24: 12,750 | G24: INR | H24: BRN-03 | I24: TXN-0021 | J24: Rental income | K24: RADHA KRISHNA | 1976-06-30
A25: 1022 | B25: ACC-664732 | C25: mohan lal | D25: 2026-08-24 | E25: debit | F25: 900 | G25: INR | H25: BRN-04 | I25: TXN-0022 | J25: Book purchase | K25: mohan lal | 1998-01-15
A26: CUST-1023 | B26: ACC-553621 | C26: Geeta Pillai | D26: 2026-08-25 | E26: Debit | F26: 2100 | G26: INR | I26: TXN-0023 | J26: School fees | K26: Geeta Pillai | 1984-05-02
A27: CUST -1024 | B27: ACC-442510 | C27: KIRAN BHAT | D27: 2026-08-25 | E27: CREDIT | F27: $7,200.00 | G27: INR | H27: BRN-02 | I27: TXN-0024 | J27: Dividend credit | K27: KIRAN BHAT | 1981-08-21
A28: CUST-1025 | B28: ACC-331399 | C28: nisha thomas | D28: 2026-08-25 | E28: debit | F28: $350 | G28: INR | H28: BRN-05 | I28: TXN-0025 | J28: Streaming subscription | K28: nisha thomas | 2001-03-07
A29: CUST-1026 | B29: ACC-220288 | C29: VISHAL AGARWAL | D29: 2026-08-25 | E29: Credit | F29: 25000 | G29: INR | H29: BRN-01 | I29: TXN-0026 | J29: Project bonus | K29: VISHAL AGARWAL | 1977-11-18
A30: CUST-1027 | B30: ACC-119177 | C30: Sunita Rao | D30: 2026-08-25 | E30: Debit | F30: 1800 | G30: INR | H30: BRN-03 | I30: TXN-0027 | J30: Monthly subscription | K30: Sunita Rao | 1993-06-06
A31: 1028 | B31: ACC-008066 | C31: rajan pillai | D31: 25/08/2026 | E31: credit | F31: 14000 | G31: INR | H31: BRN-04 | I31: TXN-0028 | J31: Salary advance | K31: rajan pillai | 1980-09-29
A33: LEGEND: 🔴 Pink fill = Duplicate row | 🟡 Yellow fill = Blank value | 🟠 Orange text = Inconsistent format | Find hidden chars & spacing issues in Notes column

Sheet Instructions
B1: KPMG Operations Analyst – Week 1 | Data Cleaning Practice
B2: Wednesday Session | Trainer Workbook
B4: 📋 What's in this workbook?
B5: Raw_Data sheet → 30 rows of messy banking transaction records with 8 data quality issues built in. Cleaned_Data sheet → Your practice area. Formulas are partially pre-filled; complete the rest as instructed.
B7: 🔧 Tasks & Formulas to Practice
B8: Task / Issue | C8: What to do | D8: Formula to use
B9: 1. Remove Duplicates | C9: Transaction_ID column has duplicate entries. Use Data → Remove Duplicates. | D9: Data tab → Remove Duplicates
B10: 2. Extra Spaces (TRIM) | C10: Customer names and notes have leading/trailing/double spaces. | D10: =TRIM(Raw_Data!C2) -> Priya Sharma
B11: 3. Non-printable chars (CLEAN) | C11: Notes column contains hidden characters that came from a system export. | D11: =CLEAN(TRIM(Raw_Data!J2)) -> Salary credit for August
B12: 4. Fix Casing (PROPER) | C12: Customer names and transaction types are in ALL CAPS or all lower. | D12: =PROPER(TRIM(Raw_Data!C2)) -> Priya Sharma
B13: 5. Text to Columns | C13: Column K has 'Name | DOB' combined. Split on '|' using Data → Text to Columns. | D13: Data tab → Text to Columns → Delimited → |
B14: 6. Handle Blanks | C14: Branch_Code has empty cells. Replace blanks with 'UNKNOWN' using IF. | D14: =IF(Raw_Data!H2="","UNKNOWN",Raw_Data!H2) -> BRN-01
B15: 7. Standardize IDs | C15: Customer_ID format is inconsistent (some miss 'CUST-' prefix, spaces inside). | D15: =IF(LEFT(TRIM(Raw_Data!A2),5)="CUST-",UPPER(TRIM(Raw_Data!A2)),"CUST-"&UPPER(TRIM(Raw_Data!A2))) -> CUST-1001
B16: 8. Standardize Financial Fields | C16: Amount column has $, commas, and text mixed. Convert to clean numbers. | D16: =VALUE(SUBSTITUTE(SUBSTITUTE(TRIM(Raw_Data!F2),"$",""),",","")) -> 15000
B18: ✅ Color Legend (Raw_Data sheet)
B19: 🔴 Red fill | C19: Duplicate rows
B20: 🟡 Yellow fill | C20: Blank / missing values
B21: 🟠 Orange text | C21: Inconsistent format (IDs, dates, amounts)
B22: ⬜ No fill | C22: Normal data (some issues may not be highlighted — find them!)

Sheet Raw_Data
A1: Customer_ID | B1: Account_Number | C1: Customer_Name | D1: Transaction_Date | E1: Transaction_Type | F1: Amount | G1: Currency | H1: Branch_Code | I1: Transaction_ID | J1: Notes | K1: Name_DOB_Combined
A2: CUST-1001 | B2: ACC-884521 | C2: Priya Sharma | D2: 2026-08-01 | E2: Credit | F2: 15000 | G2: INR | H2: BRN-01 | I2: TXN-0001 | J2: Salary credit for August | K2: Priya Sharma | 1990-04-12
A3: CUST-1002 | B3: ACC-774832 | C3: RAHUL MEHTA | D3: 2026-08-02 | E3: DEBIT | F3: $8,500.00 | G3: INR | H3: BRN-02 | I3: TXN-0002 | J3: Online transfer to vendor | K3: RAHUL MEHTA | 1985-11-30
A4: 1003 | B4: ACC-663741 | C4: ananya iyer | D4: 01/08/2026 | E4: credit | F4: 22000 | G4: INR | I4: TXN-0003 | J4: Loan disbursement [SYS] | K4: ananya iyer | 1993-07-08 | U4: 46235
A5: CUST-1004 | B5: ACC-552630 | C5: Vikram Singh | D5: 2026-08-04 | E5: Debit | F5: 3750 | G5: INR | H5: BRN-01 | I5: TXN-0004 | J5: ATM withdrawal | K5: Vikram Singh | 1978-02-25
A6: CUST-1005 | B6: ACC-441519 | C6: Sneha Nair | D6: 2026-08-05 | E6: Credit | F6: 9800 | G6: INR | H6: BRN-03 | I6: TXN-0003 | J6: Freelance payment received | K6: Sneha Nair | 1995-09-14 | U6: 46266
A7: CUST -1006 | B7: ACC-330408 | C7: AMIT PATEL | D7: 2026-08-06 | E7: DEBIT | F7: 1,200.50 | G7: INR | H7: BRN-02 | I7: TXN-0006 | J7: Utility bill payment | K7: AMIT PATEL | 1982-06-03
A8: CUST-1007 | B8: ACC-229397 | C8: ritu gupta | D8: 2026-08-07 | E8: debit | F8: 500 | G8: INR | H8: BRN-04 | I8: TXN-0007 | J8: Coffee shop payment | K8: ritu gupta | 1999-12-20
A9: CUST-1008 | B9: ACC-118286 | C9: Deepak Verma | D9: 08-Aug-2026 | E9: Credit | F9: $45,000 | G9: INR | I9: TXN-0008 | J9: Property rent collected extra | K9: Deepak Verma | 1975-03-17
A10: CUST-1009 | B10: ACC-007175 | C10: MEENA KRISHNAN | D10: 2026-08-09 | E10: Debit | F10: $2,300.00 | G10: INR | H10: BRN-03 | I10: TXN-0009 | J10: Insurance premium paid | K10: MEENA KRISHNAN | 1988-08-05 | U10: 46236
A11: CUST-1010 | B11: ACC-996064 | C11: Arjun Bose | D11: 2026-08-10 | E11: Credit | F11: 11000 | G11: INR | H11: BRN-01 | I11: TXN-0010 | J11: Dividend received | K11: Arjun Bose | 1991-01-22
A12: 1011 | B12: ACC-885953 | C12: kavya reddy | D12: 2026-08-11 | E12: debit | F12: 750 | G12: INR | H12: BRN-05 | I12: TXN-0011 | J12: Supermarket purchase | K12: kavya reddy | 1996-05-09
A13: CUST-1012 | B13: ACC-774842 | C13: SURESH PILLAI | D13: 2026-08-12 | E13: Credit | F13: N/A | G13: INR | H13: BRN-02 | I13: TXN-0012 | J13: Pending credit | K13: SURESH PILLAI | 1970-10-31
A14: 1003 | B14: ACC-663741 | C14: ananya iyer | D14: 01/08/2026 | E14: credit | F14: 22000 | G14: INR | I14: TXN-0003 | J14: Loan disbursement | K14: ananya iyer | 1993-07-08
A15: CUST-1013 | B15: ACC-553731 | C15: Pooja Desai | D15: 2026-08-14 | E15: Debit | F15: 4200 | G15: INR | H15: BRN-04 | I15: TXN-0013 | J15: EMI payment | K15: Pooja Desai | 1987-02-14
A16: CUST-1014 | B16: ACC-442620 | C16: NIKHIL JOSHI | D16: 2026-08-15 | E16: CREDIT | F16: $18,900 | G16: INR | H16: BRN-01 | I16: TXN-0014 | J16: Consulting fees | K16: NIKHIL JOSHI | 1983-07-07
A17: 1015 | B17: ACC-331509 | C17: preethi menon | D17: 2026-08-16 | E17: debit | F17: 250 | G17: INR | I17: TXN-0015 | J17: Food delivery | K17: preethi menon | 2000-11-11
A18: CUST-1016 | B18: ACC-220398 | C18: Rohit Kumar | D18: 2026-08-17 | E18: Credit | F18: 8000 | G18: INR | H18: BRN-03 | I18: TXN-0016 | J18: Part-time income | K18: Rohit Kumar | 1994-08-19
A19: CUST-1002 | B19: ACC-774832 | C19: RAHUL MEHTA | D19: 2026-08-02 | E19: DEBIT | F19: $8,500.00 | G19: INR | H19: BRN-02 | I19: TXN-0002 | J19: Online transfer to vendor | K19: RAHUL MEHTA | 1985-11-30
A20: CUST-1017 | B20: ACC-119287 | C20: LAKSHMI RAO | D20: 2026-08-19 | E20: Debit | F20: 1,050 | G20: INR | H20: BRN-05 | I20: TXN-0017 | J20: Mobile recharge | K20: LAKSHMI RAO | 1979-04-28
A21: CUST-1018 | B21: ACC-008176 | C21: Harsh Vardhan | D21: 2026-08-20 | E21: Credit | F21: 30000 | G21: INR | H21: BRN-02 | I21: TXN-0018 | J21: Quarterly bonus | K21: Harsh Vardhan | 1986-09-16
A22: CUST-1019 | B22: ACC-997065 | C22: DIVYA NAMBIAR | D22: 21-Aug-2026 | E22: DEBIT | F22: $600 | G22: INR | I22: TXN-0019 | J22: Grocery shopping | K22: DIVYA NAMBIAR | 1992-03-03
A23: CUST-1020 | B23: ACC-886954 | C23: sanjay kapoor | D23: 2026-08-22 | E23: credit | F23: 5500 | G23: INR | H23: BRN-01 | I23: TXN-0020 | J23: Freelance invoice | K23: sanjay kapoor | 1989-12-25
A24: CUST-1021 | B24: ACC-775843 | C24: RADHA KRISHNA | D24: 2026-08-23 | E24: Credit | F24: 12,750 | G24: INR | H24: BRN-03 | I24: TXN-0021 | J24: Rental income | K24: RADHA KRISHNA | 1976-06-30
A25: 1022 | B25: ACC-664732 | C25: mohan lal | D25: 2026-08-24 | E25: debit | F25: 900 | G25: INR | H25: BRN-04 | I25: TXN-0022 | J25: Book purchase | K25: mohan lal | 1998-01-15
A26: CUST-1023 | B26: ACC-553621 | C26: Geeta Pillai | D26: 2026-08-25 | E26: Debit | F26: 2100 | G26: INR | I26: TXN-0023 | J26: School fees | K26: Geeta Pillai | 1984-05-02
A27: CUST -1024 | B27: ACC-442510 | C27: KIRAN BHAT | D27: 2026-08-25 | E27: CREDIT | F27: $7,200.00 | G27: INR | H27: BRN-02 | I27: TXN-0024 | J27: Dividend credit | K27: KIRAN BHAT | 1981-08-21
A28: CUST-1025 | B28: ACC-331399 | C28: nisha thomas | D28: 2026-08-25 | E28: debit | F28: $350 | G28: INR | H28: BRN-05 | I28: TXN-0025 | J28: Streaming subscription | K28: nisha thomas | 2001-03-07
A29: CUST-1026 | B29: ACC-220288 | C29: VISHAL AGARWAL | D29: 2026-08-25 | E29: Credit | F29: 25000 | G29: INR | H29: BRN-01 | I29: TXN-0026 | J29: Project bonus | K29: VISHAL AGARWAL | 1977-11-18
A30: CUST-1027 | B30: ACC-119177 | C30: Sunita Rao | D30: 2026-08-25 | E30: Debit | F30: 1800 | G30: INR | H30: BRN-03 | I30: TXN-0027 | J30: Monthly subscription | K30: Sunita Rao | 1993-06-06
A31: 1028 | B31: ACC-008066 | C31: rajan pillai | D31: 25/08/2026 | E31: credit | F31: 14000 | G31: INR | H31: BRN-04 | I31: TXN-0028 | J31: Salary advance | K31: rajan pillai | 1980-09-29
A33: LEGEND: 🔴 Pink fill = Duplicate row | 🟡 Yellow fill = Blank value | 🟠 Orange text = Inconsistent format | Find hidden chars & spacing issues in Notes column

Sheet Cleaned_Data
A1: Customer_ID_Clean | B1: Account_Number | C1: Customer_Name_Clean | D1: Transaction_Date | E1: Transaction_Type_Clean | F1: Amount_Clean | G1: Currency | H1: Branch_Code_Clean | I1: Transaction_ID | J1: Notes_Clean
A2: ✏️ PRACTICE AREA — Apply formulas below. Rows 3-32 are pre-filled with starter formulas. Study each formula, then practice editing/extending them.
A3: =IF(LEFT(TRIM(Raw_Data!A2),5)="CUST-",UPPER(TRIM(Raw_Data!A2)),"CUST-"&UPPER(TRIM(Raw_Data!A2))) -> CUST-1001 | B3: =Raw_Data!B2 -> ACC-884521 | C3: =PROPER(TRIM(CLEAN(Raw_Data!C2))) -> Priya Sharma | D3: =Raw_Data!D2 -> 2026-08-01 | E3: =PROPER(TRIM(Raw_Data!E2)) -> Credit | F3: =IFERROR(VALUE(SUBSTITUTE(SUBSTITUTE(TRIM(Raw_Data!F2),"$",""),",","")),"CHECK") -> 15000 | G3: =Raw_Data!G2 -> INR | H3: =IF(TRIM(Raw_Data!H2)="","UNKNOWN",TRIM(Raw_Data!H2)) -> BRN-01 | I3: =Raw_Data!I2 -> TXN-0001 | J3: =PROPER(TRIM(CLEAN(Raw_Data!J2))) -> Salary Credit For August | M3: =IF(COUNTIF($J$3:J3,J3)>1,"DUPLICATE","OK") -> OK
A4: =IF(LEFT(TRIM(Raw_Data!A3),5)="CUST-",UPPER(TRIM(Raw_Data!A3)),"CUST-"&UPPER(TRIM(Raw_Data!A3))) -> CUST-1002 | B4: =Raw_Data!B3 -> ACC-774832 | C4: =PROPER(TRIM(CLEAN(Raw_Data!C3))) -> Rahul Mehta | D4: =Raw_Data!D3 -> 2026-08-02 | E4: =PROPER(TRIM(Raw_Data!E3)) -> Debit | F4: =IFERROR(VALUE(SUBSTITUTE(SUBSTITUTE(TRIM(Raw_Data!F3),"$",""),",","")),"CHECK") -> 8500 | G4: =Raw_Data!G3 -> INR | H4: =IF(TRIM(Raw_Data!H3)="","UNKNOWN",TRIM(Raw_Data!H3)) -> BRN-02 | I4: =Raw_Data!I3 -> TXN-0002 | J4: =PROPER(TRIM(CLEAN(Raw_Data!J3))) -> Online Transfer To Vendor | M4: =IF(COUNTIF($J$3:J4,J4)>1,"DUPLICATE","OK") -> OK
A5: =IF(LEFT(TRIM(Raw_Data!A4),5)="CUST-",UPPER(TRIM(Raw_Data!A4)),"CUST-"&UPPER(TRIM(Raw_Data!A4))) -> CUST-1003 | B5: =Raw_Data!B4 -> ACC-663741 | C5: =PROPER(TRIM(CLEAN(Raw_Data!C4))) -> Ananya Iyer | D5: =Raw_Data!D4 -> 01/08/2026 | E5: =PROPER(TRIM(Raw_Data!E4)) -> Credit | F5: =IFERROR(VALUE(SUBSTITUTE(SUBSTITUTE(TRIM(Raw_Data!F4),"$",""),",","")),"CHECK") -> 22000 | G5: =Raw_Data!G4 -> INR | H5: =IF(TRIM(Raw_Data!H4)="","UNKNOWN",TRIM(Raw_Data!H4)) -> UNKNOWN | I5: =Raw_Data!I4 -> TXN-0003 | J5: =PROPER(TRIM(CLEAN(Raw_Data!J4))) -> Loan Disbursement [Sys] | M5: =IF(COUNTIF($J$3:J5,J5)>1,"DUPLICATE","OK") -> OK
A6: =IF(LEFT(TRIM(Raw_Data!A5),5)="CUST-",UPPER(TRIM(Raw_Data!A5)),"CUST-"&UPPER(TRIM(Raw_Data!A5))) -> CUST-1004 | B6: =Raw_Data!B5 -> ACC-552630 | C6: =PROPER(TRIM(CLEAN(Raw_Data!C5))) -> Vikram Singh | D6: =Raw_Data!D5 -> 2026-08-04 | E6: =PROPER(TRIM(Raw_Data!E5)) -> Debit | F6: =IFERROR(VALUE(SUBSTITUTE(SUBSTITUTE(TRIM(Raw_Data!F5),"$",""),",","")),"CHECK") -> 3750 | G6: =Raw_Data!G5 -> INR | H6: =IF(TRIM(Raw_Data!H5)="","UNKNOWN",TRIM(Raw_Data!H5)) -> BRN-01 | I6: =Raw_Data!I5 -> TXN-0004 | J6: =PROPER(TRIM(CLEAN(Raw_Data!J5))) -> Atm Withdrawal | M6: =IF(COUNTIF($J$3:J6,J6)>1,"DUPLICATE","OK") -> OK
A7: =IF(LEFT(TRIM(Raw_Data!A6),5)="CUST-",UPPER(TRIM(Raw_Data!A6)),"CUST-"&UPPER(TRIM(Raw_Data!A6))) -> CUST-1005 | B7: =Raw_Data!B6 -> ACC-441519 | C7: =PROPER(TRIM(CLEAN(Raw_Data!C6))) -> Sneha Nair | D7: =Raw_Data!D6 -> 2026-08-05 | E7: =PROPER(TRIM(Raw_Data!E6)) -> Credit | F7: =IFERROR(VALUE(SUBSTITUTE(SUBSTITUTE(TRIM(Raw_Data!F6),"$",""),",","")),"CHECK") -> 9800 | G7: =Raw_Data!G6 -> INR | H7: =IF(TRIM(Raw_Data!H6)="","UNKNOWN",TRIM(Raw_Data!H6)) -> BRN-03 | I7: =Raw_Data!I6 -> TXN-0003 | J7: =PROPER(TRIM(CLEAN(Raw_Data!J6))) -> Freelance Payment Received | M7: =IF(COUNTIF($J$3:J7,J7)>1,"DUPLICATE","OK") -> OK
A8: =IF(LEFT(TRIM(Raw_Data!A7),5)="CUST-",UPPER(TRIM(Raw_Data!A7)),"CUST-"&UPPER(TRIM(Raw_Data!A7))) -> CUST-CUST -1006 | B8: =Raw_Data!B7 -> ACC-330408 | C8: =PROPER(TRIM(CLEAN(Raw_Data!C7))) -> Amit Patel | D8: =Raw_Data!D7 -> 2026-08-06 | E8: =PROPER(TRIM(Raw_Data!E7)) -> Debit | F8: =IFERROR(VALUE(SUBSTITUTE(SUBSTITUTE(TRIM(Raw_Data!F7),"$",""),",","")),"CHECK") -> 1200.5 | G8: =Raw_Data!G7 -> INR | H8: =IF(TRIM(Raw_Data!H7)="","UNKNOWN",TRIM(Raw_Data!H7)) -> BRN-02 | I8: =Raw_Data!I7 -> TXN-0006 | J8: =PROPER(TRIM(CLEAN(Raw_Data!J7))) -> Utility Bill Payment | M8: =IF(COUNTIF($J$3:J8,J8)>1,"DUPLICATE","OK") -> OK
A9: =IF(LEFT(TRIM(Raw_Data!A8),5)="CUST-",UPPER(TRIM(Raw_Data!A8)),"CUST-"&UPPER(TRIM(Raw_Data!A8))) -> CUST-1007 | B9: =Raw_Data!B8 -> ACC-229397 | C9: =PROPER(TRIM(CLEAN(Raw_Data!C8))) -> Ritu Gupta | D9: =Raw_Data!D8 -> 2026-08-07 | E9: =PROPER(TRIM(Raw_Data!E8)) -> Debit | F9: =IFERROR(VALUE(SUBSTITUTE(SUBSTITUTE(TRIM(Raw_Data!F8),"$",""),",","")),"CHECK") -> 500 | G9: =Raw_Data!G8 -> INR | H9: =IF(TRIM(Raw_Data!H8)="","UNKNOWN",TRIM(Raw_Data!H8)) -> BRN-04 | I9: =Raw_Data!I8 -> TXN-0007 | J9: =PROPER(TRIM(CLEAN(Raw_Data!J8))) -> Coffee Shop Payment | M9: =IF(COUNTIF($J$3:J9,J9)>1,"DUPLICATE","OK") -> OK
A10: =IF(LEFT(TRIM(Raw_Data!A9),5)="CUST-",UPPER(TRIM(Raw_Data!A9)),"CUST-"&UPPER(TRIM(Raw_Data!A9))) -> CUST-1008 | B10: =Raw_Data!B9 -> ACC-118286 | C10: =PROPER(TRIM(CLEAN(Raw_Data!C9))) -> Deepak Verma | D10: =Raw_Data!D9 -> 08-Aug-2026 | E10: =PROPER(TRIM(Raw_Data!E9)) -> Credit | F10: =IFERROR(VALUE(SUBSTITUTE(SUBSTITUTE(TRIM(Raw_Data!F9),"$",""),",","")),"CHECK") -> 45000 | G10: =Raw_Data!G9 -> INR | H10: =IF(TRIM(Raw_Data!H9)="","UNKNOWN",TRIM(Raw_Data!H9)) -> UNKNOWN | I10: =Raw_Data!I9 -> TXN-0008 | J10: =PROPER(TRIM(CLEAN(Raw_Data!J9))) -> Property Rent Collected Extra | M10: =IF(COUNTIF($J$3:J10,J10)>1,"DUPLICATE","OK") -> OK
A11: =IF(LEFT(TRIM(Raw_Data!A10),5)="CUST-",UPPER(TRIM(Raw_Data!A10)),"CUST-"&UPPER(TRIM(Raw_Data!A10))) -> CUST-1009 | B11: =Raw_Data!B10 -> ACC-007175 | C11: =PROPER(TRIM(CLEAN(Raw_Data!C10))) -> Meena Krishnan | D11: =Raw_Data!D10 -> 2026-08-09 | E11: =PROPER(TRIM(Raw_Data!E10)) -> Debit | F11: =IFERROR(VALUE(SUBSTITUTE(SUBSTITUTE(TRIM(Raw_Data!F10),"$",""),",","")),"CHECK") -> 2300 | G11: =Raw_Data!G10 -> INR | H11: =IF(TRIM(Raw_Data!H10)="","UNKNOWN",TRIM(Raw_Data!H10)) -> BRN-03 | I11: =Raw_Data!I10 -> TXN-0009 | J11: =PROPER(TRIM(CLEAN(Raw_Data!J10))) -> Insurance Premium Paid | M11: =IF(COUNTIF($J$3:J11,J11)>1,"DUPLICATE","OK") -> OK
A12: =IF(LEFT(TRIM(Raw_Data!A11),5)="CUST-",UPPER(TRIM(Raw_Data!A11)),"CUST-"&UPPER(TRIM(Raw_Data!A11))) -> CUST-1010 | B12: =Raw_Data!B11 -> ACC-996064 | C12: =PROPER(TRIM(CLEAN(Raw_Data!C11))) -> Arjun Bose | D12: =Raw_Data!D11 -> 2026-08-10 | E12: =PROPER(TRIM(Raw_Data!E11)) -> Credit | F12: =IFERROR(VALUE(SUBSTITUTE(SUBSTITUTE(TRIM(Raw_Data!F11),"$",""),",","")),"CHECK") -> 11000 | G12: =Raw_Data!G11 -> INR | H12: =IF(TRIM(Raw_Data!H11)="","UNKNOWN",TRIM(Raw_Data!H11)) -> BRN-01 | I12: =Raw_Data!I11 -> TXN-0010 | J12: =PROPER(TRIM(CLEAN(Raw_Data!J11))) -> Dividend Received | M12: =IF(COUNTIF($J$3:J12,J12)>1,"DUPLICATE","OK") -> OK
A13: =IF(LEFT(TRIM(Raw_Data!A12),5)="CUST-",UPPER(TRIM(Raw_Data!A12)),"CUST-"&UPPER(TRIM(Raw_Data!A12))) -> CUST-1011 | B13: =Raw_Data!B12 -> ACC-885953 | C13: =PROPER(TRIM(CLEAN(Raw_Data!C12))) -> Kavya Reddy | D13: =Raw_Data!D12 -> 2026-08-11 | E13: =PROPER(TRIM(Raw_Data!E12)) -> Debit | F13: =IFERROR(VALUE(SUBSTITUTE(SUBSTITUTE(TRIM(Raw_Data!F12),"$",""),",","")),"CHECK") -> 750 | G13: =Raw_Data!G12 -> INR | H13: =IF(TRIM(Raw_Data!H12)="","UNKNOWN",TRIM(Raw_Data!H12)) -> BRN-05 | I13: =Raw_Data!I12 -> TXN-0011 | J13: =PROPER(TRIM(CLEAN(Raw_Data!J12))) -> Supermarket Purchase | M13: =IF(COUNTIF($J$3:J13,J13)>1,"DUPLICATE","OK") -> OK
A14: =IF(LEFT(TRIM(Raw_Data!A13),5)="CUST-",UPPER(TRIM(Raw_Data!A13)),"CUST-"&UPPER(TRIM(Raw_Data!A13))) -> CUST-1012 | B14: =Raw_Data!B13 -> ACC-774842 | C14: =PROPER(TRIM(CLEAN(Raw_Data!C13))) -> Suresh Pillai | D14: =Raw_Data!D13 -> 2026-08-12 | E14: =PROPER(TRIM(Raw_Data!E13)) -> Credit | F14: =IFERROR(VALUE(SUBSTITUTE(SUBSTITUTE(TRIM(Raw_Data!F13),"$",""),",","")),"CHECK") -> CHECK | G14: =Raw_Data!G13 -> INR | H14: =IF(TRIM(Raw_Data!H13)="","UNKNOWN",TRIM(Raw_Data!H13)) -> BRN-02 | I14: =Raw_Data!I13 -> TXN-0012 | J14: =PROPER(TRIM(CLEAN(Raw_Data!J13))) -> Pending Credit | M14: =IF(COUNTIF($J$3:J14,J14)>1,"DUPLICATE","OK") -> OK
... A32: =IF(LEFT(TRIM(Raw_Data!A31),5)="CUST-",UPPER(TRIM(Raw_Data!A31)),"CUST-"&UPPER(TRIM(Raw_Data!A31))) -> CUST-1028 | B32: =Raw_Data!B31 -> ACC-008066 | C32: =PROPER(TRIM(CLEAN(Raw_Data!C31))) -> Rajan Pillai | D32: =Raw_Data!D31 -> 25/08/2026 | E32: =PROPER(TRIM(Raw_Data!E31)) -> Credit | F32: =IFERROR(VALUE(SUBSTITUTE(SUBSTITUTE(TRIM(Raw_Data!F31),"$",""),",","")),"CHECK") -> 14000 | G32: =Raw_Data!G31 -> INR | H32: =IF(TRIM(Raw_Data!H31)="","UNKNOWN",TRIM(Raw_Data!H31)) -> BRN-04 | I32: =Raw_Data!I31 -> TXN-0028 | J32: =PROPER(TRIM(CLEAN(Raw_Data!J31))) -> Salary Advance | M32: =IF(COUNTIF($J$3:J32,J32)>1,"DUPLICATE","OK") -> OK
A34: 💡 Blue cells = Excel formulas (click to see) | After removing duplicates from Raw_Data, re-check which rows disappear here | Column D (Date): practice Text-to-Columns & date formatting manually in Excel
A36: 🏆 CHALLENGE TASKS — Complete these without hints
A37: C1 | B37: Count how many Customer_IDs were missing the 'CUST-' prefix in Raw_Data | G37: Hint: COUNTIF + wildcard on Raw_Data!A:A
A38: C2 | B38: Count rows where Branch_Code was blank in Raw_Data | G38: Hint: COUNTBLANK(Raw_Data!H2:H31)
A39: C3 | B39: Calculate total Amount after cleaning (exclude 'CHECK' errors) | G39: Hint: SUMIF on column F of this sheet
A40: C4 | B40: Find how many duplicate Transaction_IDs exist in Raw_Data | G40: Hint: COUNTIF(Raw_Data!I:I, Raw_Data!I2) > 1
A41: C5 | B41: List unique Transaction_Types using PROPER casing | G41: Hint: Use Remove Duplicates on a copy of col E
A43: Your answers (type formulas in column B beside each challenge number above):
